likelihood/__init__.py
likelihood/main.py
likelihood/pipes.py
likelihood/graph/__init__.py
likelihood/graph/_nn.py
likelihood/graph/graph.py
likelihood/graph/nn.py
likelihood/models/__init__.py
likelihood/models/environments.py
likelihood/models/hmm.py
likelihood/models/regression.py
likelihood/models/simulation.py
likelihood/models/utils.py
likelihood/models/deep/__init__.py
likelihood/models/deep/_autoencoders.py
likelihood/models/deep/_predictor.py
likelihood/models/deep/autoencoders.py
likelihood/models/deep/bandit.py
likelihood/models/deep/gan.py
likelihood/models/deep/predictor.py
likelihood/models/deep/rl.py
likelihood/tools/__init__.py
likelihood/tools/cat_embed.py
likelihood/tools/figures.py
likelihood/tools/impute.py
likelihood/tools/models_tools.py
likelihood/tools/numeric_tools.py
likelihood/tools/reports.py
likelihood/tools/tools.py
likelihood-2.1.2.dist-info/licenses/LICENSE
likelihood-2.1.2.dist-info/METADATA
likelihood-2.1.2.dist-info/WHEEL
likelihood-2.1.2.dist-info/top_level.txt
likelihood-2.1.2.dist-info/RECORD
